aminoacid/__init__.py
aminoacid/_socket.py
aminoacid/abc.py
aminoacid/client.py
aminoacid/exceptions.py
aminoacid/util/__init__.py
aminoacid/util/commands.py
aminoacid/util/enums.py
aminoacid/util/events.py
aminoacid-0.1.5.dist-info/LICENSE
aminoacid-0.1.5.dist-info/METADATA
aminoacid-0.1.5.dist-info/WHEEL
aminoacid-0.1.5.dist-info/top_level.txt
aminoacid-0.1.5.dist-info/RECORD
