Metadata-Version: 2.1
Name: aminoacid
Version: 0.1.5
Summary: Async library for creating Bots for amino
Home-page: https://github.com/okok7711/AminoAcid
Author: okok7711
Author-email: okok7711@etstun.de
License: MIT License
Keywords: amino,internet,bot,async
Classifier: Intended Audience :: Developers
Classifier: License :: OSI Approved :: MIT License
Classifier: Operating System :: OS Independent
Classifier: Programming Language :: Python
Classifier: Programming Language :: Python :: 3.5
Classifier: Programming Language :: Python :: 3.6
Classifier: Programming Language :: Python :: 3.7
Classifier: Programming Language :: Python :: 3.8
Classifier: Programming Language :: Python :: 3.9
Classifier: Programming Language :: Python :: 3.10
License-File: LICENSE
Requires-Dist: aiohttp
